src/Modulos/Control/selector_numero_display.sv
module selector_numero_display (
    input  logic [1:0] seleccion_display,
    input  logic       sel_resultado,

    input  logic [5:0] numero_a,
    input  logic [3:0] numero_b,
    input  logic [5:0] cociente,
    input  logic [3:0] residuo,

    output logic [5:0] numero_display,
    output logic       display_error
);

    always_comb begin
        numero_display = 6'd0;
        display_error  = 1'b0;

        case (seleccion_display)

            2'd0: begin
                numero_display = numero_a;
            end

            2'd1: begin
                numero_display = {2'b00, numero_b};
            end

            2'd2: begin
                if (sel_resultado)
                    numero_display = {2'b00, residuo};
                else
                    numero_display = cociente;
            end

            2'd3: begin
                numero_display = 6'd0;
                display_error  = 1'b1;
            end

            default: begin
                numero_display = 6'd0;
                display_error  = 1'b0;
            end

        endcase
    end

endmodule

src/Modulos/Control/constructor_numero.sv
module constructor_numero #(
    parameter int WIDTH       = 6,
    parameter int MAX_DIGITOS = 2,
    parameter int MAX_VAL     = 63
)(
    input  logic             clk,
    input  logic             rst,
    input  logic             limpiar,
    input  logic             cargar_digito,
    input  logic             borrar,
    input  logic [3:0]       digito,

    output logic [WIDTH-1:0] numero,
    output logic [1:0]       cantidad_digitos,
    output logic             lleno,
    output logic             es_cero
);

    localparam int CALC_WIDTH = WIDTH + 4;

    logic cargar_r;
    logic borrar_r;
    logic [3:0] digito_r;
    logic [3:0] primer_digito;

    logic [CALC_WIDTH-1:0] numero_ext;
    logic [CALC_WIDTH-1:0] digito_ext;
    logic [CALC_WIDTH-1:0] primer_ext;
    logic [CALC_WIDTH-1:0] candidato;

    assign lleno   = (cantidad_digitos >= MAX_DIGITOS[1:0]);
    assign es_cero = (numero == '0);

    // 0-7: digito_r[3]==0 / 8-9: explícito
    logic es_digito_r;
    assign es_digito_r = (digito_r[3] == 1'b0) ||
                         (digito_r == 4'd8)     ||
                         (digito_r == 4'd9);

    always_comb begin
        numero_ext = '0;
        numero_ext[WIDTH-1:0] = numero;

        digito_ext = '0;
        digito_ext[3:0] = digito_r;

        primer_ext = '0;
        primer_ext[3:0] = primer_digito;

        candidato = numero_ext;

        if (cantidad_digitos == 2'd0)
            candidato = digito_ext;
        else if (cantidad_digitos == 2'd1)
            candidato = (numero_ext << 3) + (numero_ext << 1) + digito_ext;
    end

    always_ff @(posedge clk or posedge rst) begin
        if (rst) begin
            numero           <= '0;
            cantidad_digitos <= 2'd0;
            primer_digito    <= 4'd0;
            cargar_r         <= 1'b0;
            borrar_r         <= 1'b0;
            digito_r         <= 4'd0;
        end
        else begin
            cargar_r <= cargar_digito;
            borrar_r <= borrar;
            digito_r <= digito;

            if (limpiar) begin
                numero           <= '0;
                cantidad_digitos <= 2'd0;
                primer_digito    <= 4'd0;
                cargar_r         <= 1'b0;
                borrar_r         <= 1'b0;
                digito_r         <= 4'd0;
            end
            else if (borrar_r && cantidad_digitos > 2'd0) begin
                if (cantidad_digitos == 2'd2) begin
                    numero           <= primer_ext[WIDTH-1:0];
                    cantidad_digitos <= 2'd1;
                end
                else begin
                    numero           <= '0;
                    cantidad_digitos <= 2'd0;
                    primer_digito    <= 4'd0;
                end
            end
            else if (cargar_r && !lleno && es_digito_r) begin
                if (candidato <= CALC_WIDTH'(MAX_VAL)) begin
                    numero <= candidato[WIDTH-1:0];

                    if (cantidad_digitos == 2'd0) begin
                        cantidad_digitos <= 2'd1;
                        primer_digito    <= digito_r;
                    end
                    else if (cantidad_digitos == 2'd1) begin
                        cantidad_digitos <= 2'd2;
                    end
                end
            end
        end
    end

endmodule

src/Modulos/Control/control_entrada_fsm.sv
module control_entrada_fsm (
    input  logic       clk,
    input  logic       rst,

    input  logic       key_valid,
    input  logic [3:0] key_code,

    input  logic       a_lleno,
    input  logic       b_lleno,
    input  logic       b_es_cero,

    input  logic       done,

    output logic       limpiar,
    output logic       cargar_a,
    output logic       cargar_b,
    output logic       borrar_a,
    output logic       borrar_b,
    output logic       valid,

    output logic       error,
    output logic       sel_resultado,
    output logic [1:0] seleccion_display
);

    localparam logic [2:0] INGRESO_A  = 3'd0;
    localparam logic [2:0] INGRESO_B  = 3'd1;
    localparam logic [2:0] CALCULANDO = 3'd2;
    localparam logic [2:0] RESULTADO  = 3'd3;
    localparam logic [2:0] ERROR      = 3'd4;

    logic [2:0] estado;

    // 0-7: key_code[3]==0 / 8-9: explícito
    logic es_digito;
    assign es_digito = (key_code[3] == 1'b0) ||
                       (key_code == 4'd8)     ||
                       (key_code == 4'd9);

    always_ff @(posedge clk or posedge rst) begin
        if (rst) begin
            estado        <= INGRESO_A;
            sel_resultado <= 1'b0;
        end
        else begin
            if (key_valid && (key_code == 4'hC || key_code == 4'hD)) begin
                estado        <= INGRESO_A;
                sel_resultado <= 1'b0;
            end
            else begin
                case (estado)
                    INGRESO_A: begin
                        if (key_valid && key_code == 4'hA)
                            estado <= INGRESO_B;
                    end

                    INGRESO_B: begin
                        if (key_valid && key_code == 4'hA) begin
                            sel_resultado <= 1'b0;
                            if (b_es_cero)
                                estado <= ERROR;
                            else
                                estado <= CALCULANDO;
                        end
                    end

                    CALCULANDO: begin
                        if (done)
                            estado <= RESULTADO;
                    end

                    RESULTADO: begin
                        if (key_valid && (key_code == 4'hE || key_code == 4'hF))
                            sel_resultado <= ~sel_resultado;
                    end

                    ERROR: begin
                        // Sale solo con C o D
                    end

                    default: estado <= INGRESO_A;
                endcase
            end
        end
    end

    always_comb begin
        limpiar           = 1'b0;
        cargar_a          = 1'b0;
        cargar_b          = 1'b0;
        borrar_a          = 1'b0;
        borrar_b          = 1'b0;
        valid             = 1'b0;
        error             = 1'b0;
        seleccion_display = 2'd0;

        case (estado)
            INGRESO_A:  seleccion_display = 2'd0;
            INGRESO_B:  seleccion_display = 2'd1;
            CALCULANDO: seleccion_display = 2'd2;
            RESULTADO:  seleccion_display = 2'd2;
            ERROR:      seleccion_display = 2'd3;
            default:    seleccion_display = 2'd0;
        endcase

        if (estado == ERROR)
            error = 1'b1;

        if (key_valid) begin
            if (key_code == 4'hC || key_code == 4'hD) begin
                limpiar = 1'b1;
            end
            else begin
                case (estado)
                    INGRESO_A: begin
                        if (es_digito && !a_lleno)
                            cargar_a = 1'b1;
                        else if (key_code == 4'hB)
                            borrar_a = 1'b1;
                    end

                    INGRESO_B: begin
                        if (es_digito && !b_lleno)
                            cargar_b = 1'b1;
                        else if (key_code == 4'hB)
                            borrar_b = 1'b1;
                        else if (key_code == 4'hA && !b_es_cero)
                            valid = 1'b1;
                    end

                    default: ;
                endcase
            end
        end
    end

endmodule

src/Modulos/Control/reset_inicio.sv
module reset_inicio #(
    parameter int CICLOS = 5_000_000
)(
    input  logic clk,
    input  logic rst_n,
    output logic rst
);

    logic [22:0] contador;

    always_ff @(posedge clk or negedge rst_n) begin
        if (!rst_n) begin
            contador <= 23'd0;
            rst      <= 1'b1;
        end else begin
            if (contador < CICLOS) begin
                contador <= contador + 23'd1;
                rst      <= 1'b1;
            end else begin
                rst      <= 1'b0;
            end
        end
    end

endmodule

src/UnidadPrincipal/sim/tb_control_entrada.sv
`timescale 1ns/1ps

module tb_control_entrada;

    // ------------------------------------------------------------
    // Reloj y reset
    // ------------------------------------------------------------
    logic clk;
    logic rst_n;
    logic rst;

    initial clk = 1'b0;
    always #5 clk = ~clk;   // Periodo = 10 ns

    // Reset de inicio con pocos ciclos para simulacion
    reset_inicio #(
        .CICLOS(3)
    ) u_reset_inicio (
        .clk   (clk),
        .rst_n (rst_n),
        .rst   (rst)
    );

    // ------------------------------------------------------------
    // Senales tipo teclado
    // ------------------------------------------------------------
    logic       key_valid;
    logic [3:0] key_code;

    // ------------------------------------------------------------
    // Senales del control
    // ------------------------------------------------------------
    logic limpiar;
    logic cargar_a;
    logic cargar_b;
    logic borrar_a;
    logic borrar_b;
    logic valid;
    logic error;
    logic sel_resultado;
    logic [1:0] seleccion_display;

    // ------------------------------------------------------------
    // Numeros construidos
    // ------------------------------------------------------------
    logic [5:0] numero_a;
    logic [3:0] numero_b;

    logic [1:0] cantidad_a;
    logic [1:0] cantidad_b;

    logic a_lleno;
    logic b_lleno;
    logic a_es_cero;
    logic b_es_cero;

    // ------------------------------------------------------------
    // Resultado simulado de division
    // ------------------------------------------------------------
    logic [5:0] cociente;
    logic [3:0] residuo;
    logic       done;

    // ------------------------------------------------------------
    // Display
    // ------------------------------------------------------------
    logic [5:0] numero_display;
    logic       display_error;

    // ------------------------------------------------------------
    // DUTs
    // ------------------------------------------------------------

    control_entrada_fsm u_control (
        .clk                (clk),
        .rst                (rst),
        .key_valid          (key_valid),
        .key_code           (key_code),
        .a_lleno            (a_lleno),
        .b_lleno            (b_lleno),
        .b_es_cero          (b_es_cero),
        .done               (done),
        .limpiar            (limpiar),
        .cargar_a           (cargar_a),
        .cargar_b           (cargar_b),
        .borrar_a           (borrar_a),
        .borrar_b           (borrar_b),
        .valid              (valid),
        .error              (error),
        .sel_resultado      (sel_resultado),
        .seleccion_display  (seleccion_display)
    );

    constructor_numero #(
        .WIDTH       (6),
        .MAX_DIGITOS (2),
        .MAX_VAL     (63)
    ) u_constructor_a (
        .clk              (clk),
        .rst              (rst),
        .limpiar          (limpiar),
        .cargar_digito    (cargar_a),
        .borrar           (borrar_a),
        .digito           (key_code),
        .numero           (numero_a),
        .cantidad_digitos (cantidad_a),
        .lleno            (a_lleno),
        .es_cero          (a_es_cero)
    );

    constructor_numero #(
        .WIDTH       (4),
        .MAX_DIGITOS (1),
        .MAX_VAL     (9)
    ) u_constructor_b (
        .clk              (clk),
        .rst              (rst),
        .limpiar          (limpiar),
        .cargar_digito    (cargar_b),
        .borrar           (borrar_b),
        .digito           (key_code),
        .numero           (numero_b),
        .cantidad_digitos (cantidad_b),
        .lleno            (b_lleno),
        .es_cero          (b_es_cero)
    );

    selector_numero_display u_selector (
        .seleccion_display (seleccion_display),
        .sel_resultado     (sel_resultado),
        .numero_a          (numero_a),
        .numero_b          (numero_b),
        .cociente          (cociente),
        .residuo           (residuo),
        .numero_display    (numero_display),
        .display_error     (display_error)
    );

    // ------------------------------------------------------------
    // Modelo simple de la division.
    // Cuando el control levanta valid, este bloque calcula el
    // cociente/residuo y levanta done por un ciclo.
    // ------------------------------------------------------------
    always_ff @(posedge clk or posedge rst) begin
        if (rst) begin
            cociente <= 6'd0;
            residuo  <= 4'd0;
            done     <= 1'b0;
        end else begin
            if (valid) begin
                cociente <= numero_a / numero_b;
                residuo  <= numero_a % numero_b;
                done     <= 1'b1;
            end else begin
                done     <= 1'b0;
            end
        end
    end

    // ------------------------------------------------------------
    // Utilidades del testbench
    // ------------------------------------------------------------
    int errores;

    task automatic presionar_tecla(input logic [3:0] tecla);
        begin
            @(negedge clk);
            key_code  = tecla;
            key_valid = 1'b1;

            @(negedge clk);
            key_valid = 1'b0;
            key_code  = 4'h0;

            // El constructor_numero tiene registros internos
            // cargar_r y digito_r, por eso se esperan ciclos extra.
            repeat (2) @(posedge clk);
            #1;
        end
    endtask

    task automatic verificar(input bit condicion, input string mensaje);
        begin
            if (!condicion) begin
                errores++;
                $error("FALLO: %s", mensaje);
            end else begin
                $display("OK: %s", mensaje);
            end
        end
    endtask

    task automatic mostrar_estado(input string titulo);
        begin
            $display("\n[%0t] %s", $time, titulo);
            $display("A=%0d cantA=%0d llenoA=%0b | B=%0d cantB=%0d llenoB=%0b ceroB=%0b", 
                     numero_a, cantidad_a, a_lleno, numero_b, cantidad_b, b_lleno, b_es_cero);
            $display("sel_disp=%0d sel_res=%0b display=%0d display_error=%0b valid=%0b done=%0b error=%0b", 
                     seleccion_display, sel_resultado, numero_display, display_error, valid, done, error);
        end
    endtask

    // ------------------------------------------------------------
    // Estimulos principales
    // ------------------------------------------------------------
    initial begin
        errores   = 0;
        rst_n     = 1'b0;
        key_valid = 1'b0;
        key_code  = 4'h0;

        $dumpfile("tb_control_entrada.vcd");
        $dumpvars(0, tb_control_entrada);

        // Liberar reset externo
        repeat (2) @(posedge clk);
        rst_n = 1'b1;

        // Esperar a que reset_inicio baje rst
        wait (rst == 1'b0);
        repeat (2) @(posedge clk);
        #1;

        mostrar_estado("Despues de reset");
        verificar(numero_a == 6'd0, "A inicia en 0");
        verificar(numero_b == 4'd0, "B inicia en 0");
        verificar(seleccion_display == 2'd0, "Display inicia mostrando A");
        verificar(error == 1'b0, "No hay error inicial");

        // ========================================================
        // Caso 1: Ingresar A=42, B=7, calcular 42/7
        // Teclas: 4, 2, A, 7, A
        // ========================================================
        $display("\n================ CASO 1: 42 / 7 = 6 r 0 ================");

        presionar_tecla(4'd4);
        verificar(numero_a == 6'd4, "Despues de tecla 4, A = 4");
        verificar(cantidad_a == 2'd1, "A tiene 1 digito");

        presionar_tecla(4'd2);
        verificar(numero_a == 6'd42, "Despues de tecla 2, A = 42");
        verificar(cantidad_a == 2'd2, "A tiene 2 digitos");
        verificar(a_lleno == 1'b1, "A esta lleno");

        presionar_tecla(4'd9);
        verificar(numero_a == 6'd42, "Si A esta lleno, otro digito no cambia A");

        presionar_tecla(4'hA);
        verificar(seleccion_display == 2'd1, "Con tecla A se pasa a ingreso de B");
        verificar(numero_display == 6'd0, "Al entrar a B, display muestra B=0");

        presionar_tecla(4'd7);
        verificar(numero_b == 4'd7, "Despues de tecla 7, B = 7");
        verificar(b_lleno == 1'b1, "B esta lleno con 1 digito");

        presionar_tecla(4'hA);
        mostrar_estado("Despues de calcular 42/7");
        verificar(seleccion_display == 2'd2, "Despues de calcular, display muestra resultado");
        verificar(error == 1'b0, "No hay error en 42/7");
        verificar(cociente == 6'd6, "Cociente = 6");
        verificar(residuo == 4'd0, "Residuo = 0");
        verificar(sel_resultado == 1'b0, "Por defecto se muestra cociente");
        verificar(numero_display == 6'd6, "Display muestra cociente 6");

        presionar_tecla(4'hE);
        verificar(sel_resultado == 1'b1, "Tecla E alterna a residuo");
        verificar(numero_display == 6'd0, "Display muestra residuo 0");

        presionar_tecla(4'hF);
        verificar(sel_resultado == 1'b0, "Tecla F alterna de vuelta a cociente");
        verificar(numero_display == 6'd6, "Display vuelve a mostrar cociente 6");

        // ========================================================
        // Caso 2: Limpiar con C
        // ========================================================
        $display("\n================ CASO 2: limpiar con C ================");
        presionar_tecla(4'hC);
        mostrar_estado("Despues de limpiar");
        verificar(numero_a == 6'd0, "C limpia A");
        verificar(numero_b == 4'd0, "C limpia B");
        verificar(cantidad_a == 2'd0, "C limpia cantidad de digitos de A");
        verificar(cantidad_b == 2'd0, "C limpia cantidad de digitos de B");
        verificar(seleccion_display == 2'd0, "C vuelve a ingreso de A");
        verificar(error == 1'b0, "C quita error si existia");

        // ========================================================
        // Caso 3: Borrar digitos de A
        // Teclas: 5, 6, B, B
        // ========================================================
        $display("\n================ CASO 3: borrar digitos ================");
        presionar_tecla(4'd5);
        presionar_tecla(4'd6);
        verificar(numero_a == 6'd56, "A = 56 antes de borrar");

        presionar_tecla(4'hB);
        verificar(numero_a == 6'd5, "Primer borrar deja A = 5");
        verificar(cantidad_a == 2'd1, "A queda con 1 digito");

        presionar_tecla(4'hB);
        verificar(numero_a == 6'd0, "Segundo borrar deja A = 0");
        verificar(cantidad_a == 2'd0, "A queda con 0 digitos");

        // ========================================================
        // Caso 4: Evitar valor fuera de rango A > 63
        // Teclas: C, 6, 4. El 64 no debe cargarse.
        // ========================================================
        $display("\n================ CASO 4: limite MAX_VAL de A = 63 ================");
        presionar_tecla(4'hC);
        presionar_tecla(4'd6);
        presionar_tecla(4'd4);
        verificar(numero_a == 6'd6, "A no acepta 64 porque MAX_VAL = 63");
        verificar(cantidad_a == 2'd1, "Cantidad de A se mantiene en 1 digito");

        // ========================================================
        // Caso 5: Error por division entre cero
        // Teclas: C, 1, 2, A, 0, A
        // ========================================================
        $display("\n================ CASO 5: division entre cero ================");
        presionar_tecla(4'hC);
        presionar_tecla(4'd1);
        presionar_tecla(4'd2);
        presionar_tecla(4'hA);
        presionar_tecla(4'd0);
        presionar_tecla(4'hA);
        mostrar_estado("Despues de intentar 12/0");
        verificar(error == 1'b1, "12/0 activa error");
        verificar(seleccion_display == 2'd3, "En error, seleccion_display = 3");
        verificar(display_error == 1'b1, "Selector activa display_error");

        presionar_tecla(4'hD);
        verificar(error == 1'b0, "D limpia el estado de error");
        verificar(numero_a == 6'd0, "D limpia A");
        verificar(numero_b == 4'd0, "D limpia B");
        verificar(seleccion_display == 2'd0, "D vuelve a ingreso de A");

        // --------------------------------------------------------
        // Resultado final
        // --------------------------------------------------------
        if (errores == 0) begin
            $display("\n========================================================");
            $display("TODAS LAS PRUEBAS PASARON CORRECTAMENTE");
            $display("========================================================");
        end else begin
            $display("\n========================================================");
            $display("PRUEBAS TERMINADAS CON %0d ERROR(ES)", errores);
            $display("========================================================");
        end

        $finish;
    end

endmodule

src/UnidadPrincipal/build/tb_control_entrada.vcd
$date
	Tue Jun 09 18:41:58 2026
$end
$version
	Icarus Verilog
$end
$timescale
	1ps
$end
$scope module tb_control_entrada $end
$var wire 1 ! valid $end
$var wire 2 " seleccion_display [1:0] $end
$var wire 1 # sel_resultado $end
$var wire 1 $ rst $end
$var wire 6 % numero_display [5:0] $end
$var wire 4 & numero_b [3:0] $end
$var wire 6 ' numero_a [5:0] $end
$var wire 1 ( limpiar $end
$var wire 1 ) error $end
$var wire 1 * display_error $end
$var wire 1 + cargar_b $end
$var wire 1 , cargar_a $end
$var wire 2 - cantidad_b [1:0] $end
$var wire 2 . cantidad_a [1:0] $end
$var wire 1 / borrar_b $end
$var wire 1 0 borrar_a $end
$var wire 1 1 b_lleno $end
$var wire 1 2 b_es_cero $end
$var wire 1 3 a_lleno $end
$var wire 1 4 a_es_cero $end
$var reg 1 5 clk $end
$var reg 6 6 cociente [5:0] $end
$var reg 1 7 done $end
$var reg 4 8 key_code [3:0] $end
$var reg 1 9 key_valid $end
$var reg 4 : residuo [3:0] $end
$var reg 1 ; rst_n $end
$var integer 32 < errores [31:0] $end
$scope module u_constructor_a $end
$var wire 1 5 clk $end
$var wire 4 = digito [3:0] $end
$var wire 1 > es_digito_r $end
$var wire 1 $ rst $end
$var wire 1 3 lleno $end
$var wire 1 ( limpiar $end
$var wire 1 4 es_cero $end
$var wire 1 , cargar_digito $end
$var wire 1 0 borrar $end
$var parameter 32 ? CALC_WIDTH $end
$var parameter 32 @ MAX_DIGITOS $end
$var parameter 32 A MAX_VAL $end
$var parameter 32 B WIDTH $end
$var reg 1 C borrar_r $end
$var reg 10 D candidato [9:0] $end
$var reg 2 E cantidad_digitos [1:0] $end
$var reg 1 F cargar_r $end
$var reg 10 G digito_ext [9:0] $end
$var reg 4 H digito_r [3:0] $end
$var reg 6 I numero [5:0] $end
$var reg 10 J numero_ext [9:0] $end
$var reg 4 K primer_digito [3:0] $end
$var reg 10 L primer_ext [9:0] $end
$upscope $end
$scope module u_constructor_b $end
$var wire 1 5 clk $end
$var wire 4 M digito [3:0] $end
$var wire 1 N es_digito_r $end
$var wire 1 $ rst $end
$var wire 1 1 lleno $end
$var wire 1 ( limpiar $end
$var wire 1 2 es_cero $end
$var wire 1 + cargar_digito $end
$var wire 1 / borrar $end
$var parameter 32 O CALC_WIDTH $end
$var parameter 32 P MAX_DIGITOS $end
$var parameter 32 Q MAX_VAL $end
$var parameter 32 R WIDTH $end
$var reg 1 S borrar_r $end
$var reg 8 T candidato [7:0] $end
$var reg 2 U cantidad_digitos [1:0] $end
$var reg 1 V cargar_r $end
$var reg 8 W digito_ext [7:0] $end
$var reg 4 X digito_r [3:0] $end
$var reg 4 Y numero [3:0] $end
$var reg 8 Z numero_ext [7:0] $end
$var reg 4 [ primer_digito [3:0] $end
$var reg 8 \ primer_ext [7:0] $end
$upscope $end
$scope module u_control $end
$var wire 1 3 a_lleno $end
$var wire 1 2 b_es_cero $end
$var wire 1 1 b_lleno $end
$var wire 1 5 clk $end
$var wire 1 7 done $end
$var wire 1 ] es_digito $end
$var wire 4 ^ key_code [3:0] $end
$var wire 1 9 key_valid $end
$var wire 1 $ rst $end
$var parameter 3 _ CALCULANDO $end
$var parameter 3 ` ERROR $end
$var parameter 3 a INGRESO_A $end
$var parameter 3 b INGRESO_B $end
$var parameter 3 c RESULTADO $end
$var reg 1 0 borrar_a $end
$var reg 1 / borrar_b $end
$var reg 1 , cargar_a $end
$var reg 1 + cargar_b $end
$var reg 1 ) error $end
$var reg 3 d estado [2:0] $end
$var reg 1 ( limpiar $end
$var reg 1 # sel_resultado $end
$var reg 2 e seleccion_display [1:0] $end
$var reg 1 ! valid $end
$upscope $end
$scope module u_reset_inicio $end
$var wire 1 5 clk $end
$var wire 1 ; rst_n $end
$var parameter 32 f CICLOS $end
$var reg 23 g contador [22:0] $end
$var reg 1 $ rst $end
$upscope $end
$scope module u_selector $end
$var wire 6 h cociente [5:0] $end
$var wire 6 i numero_a [5:0] $end
$var wire 4 j numero_b [3:0] $end
$var wire 4 k residuo [3:0] $end
$var wire 1 # sel_resultado $end
$var wire 2 l seleccion_display [1:0] $end
$var reg 1 * display_error $end
$var reg 6 m numero_display [5:0] $end
$upscope $end
$scope task mostrar_estado $end
$upscope $end
$scope task presionar_tecla $end
$upscope $end
$scope task verificar $end
$upscope $end
$upscope $end
$enddefinitions $end
$comment Show the parameter values. $end
$dumpall
b11 f
b11 c
b1 b
b0 a
b100 `
b10 _
b100 R
b1001 Q
b1 P
b1000 O
b110 B
b111111 A
b10 @
b1010 ?
$end
#0
$dumpvars
b0 m
b0 l
b0 k
b0 j
b0 i
b0 h
b0 g
b0 e
b0 d
b0 ^
1]
b0 \
b0 [
b0 Z
b0 Y
b0 X
b0 W
0V
b0 U
b0 T
0S
1N
b0 M
b0 L
b0 K
b0 J
b0 I
b0 H
b0 G
0F
b0 E
b0 D
0C
1>
b0 =
b0 <
0;
b0 :
09
b0 8
07
b0 6
05
14
03
12
01
00
0/
b0 .
b0 -
0,
0+
0*
0)
0(
b0 '
b0 &
b0 %
1$
0#
b0 "
0!
$end
#5000
15
#10000
05
#15000
b1 g
1;
15
#20000
05
#25000
b10 g
15
#30000
05
#35000
b11 g
15
#40000
05
#45000
0$
15
#50000
05
#55000
15
#60000
05
#65000
15
#70000
1,
19
b100 8
b100 =
b100 M
b100 ^
05
#75000
b100 D
b100 G
b100 T
b100 W
b100 H
1F
b100 X
15
#80000
0,
b0 8
b0 =
b0 M
b0 ^
09
05
#85000
b0 T
b0 W
b100 %
b100 m
b101000 D
b100 L
b0 G
b100 J
b0 X
b100 K
b1 .
b1 E
04
b100 '
b100 I
b100 i
b0 H
0F
15
#90000
05
#95000
15
#100000
1,
19
b10 8
b10 =
b10 M
b10 ^
05
#105000
b10 T
b10 W
b101010 D
b100 L
b10 G
b100 J
b10 X
b10 H
1F
15
#110000
0,
b0 8
b0 =
b0 M
b0 ^
09
05
#115000
b101010 %
b101010 m
b100 L
b0 G
b101010 J
b0 T
b0 W
13
b10 .
b10 E
b101010 '
b101010 I
b101010 i
b0 H
0F
b0 X
15
#120000
05
#125000
15
#130000
19
b1001 8
b1001 =
b1001 M
b1001 ^
05
#135000
b100 L
b1001 G
b101010 J
b1001 T
b1001 W
b1001 H
b1001 X
15
#140000
1]
b0 8
b0 =
b0 M
b0 ^
09
05
#145000
b0 T
b0 W
1N
b100 L
b0 G
b101010 J
1>
b0 X
b0 H
15
#150000
05
#155000
15
#160000
0]
19
b1010 8
b1010 =
b1010 M
b1010 ^
05
#165000
0N
0>
b0 %
b0 m
b1010 T
b1010 W
b100 L
b1010 G
b101010 J
b1 "
b1 e
b1 l
b1010 X
b1010 H
b1 d
15
#170000
1]
b1 "
b1 e
b1 l
b0 8
b0 =
b0 M
b0 ^
09
05
#175000
1>
1N
b100 L
b0 G
b101010 J
b0 T
b0 W
b0 H
b0 X
15
#180000
05
#185000
15
#190000
1+
b1 "
b1 e
b1 l
19
b111 8
b111 =
b111 M
b111 ^
05
#195000
b100 L
b111 G
b101010 J
b111 T
b111 W
b111 H
b111 X
1V
15
#200000
b1 "
b1 e
b1 l
0+
b0 8
b0 =
b0 M
b0 ^
09
05
#205000
b1 "
b1 e
b1 l
b111 %
b111 m
b1000110 T
b111 \
b0 W
b111 Z
b100 L
b0 G
b101010 J
b111 [
11
b1 -
b1 U
02
b111 &
b111 Y
b111 j
b0 X
0V
b0 H
15
#210000
05
#215000
15
#220000
0]
b111 %
b111 m
1!
b1 "
b1 e
b1 l
19
b1010 8
b1010 =
b1010 M
b1010 ^
05
#225000
0N
0>
b110 %
b110 m
b1010000 T
b111 \
b1010 W
b111 Z
b100 L
b1010 G
b101010 J
b10 "
b10 e
b10 l
0!
17
b110 6
b110 h
b1010 X
b1010 H
b10 d
15
#230000
1]
b110 %
b110 m
b10 "
b10 e
b10 l
b0 8
b0 =
b0 M
b0 ^
09
05
#235000
1>
1N
b110 %
b110 m
b10 "
b10 e
b10 l
b100 L
b0 G
b101010 J
b1000110 T
b111 \
b0 W
b111 Z
b11 d
b0 H
b0 X
07
15
#240000
05
#245000
15
#250000
0]
b110 %
b110 m
b10 "
b10 e
b10 l
19
b1110 8
b1110 =
b1110 M
b1110 ^
05
#255000
0>
0N
b0 %
b0 m
b100 L
b1110 G
b101010 J
b1010100 T
b111 \
b1110 W
b111 Z
1#
b1110 H
b1110 X
15
#260000
1]
b10 "
b10 e
b10 l
b0 8
b0 =
b0 M
b0 ^
09
05
#265000
1N
1>
b1000110 T
b111 \
b0 W
b111 Z
b100 L
b0 G
b101010 J
b0 X
b0 H
15
#270000
05
#275000
15
#280000
0]
b10 "
b10 e
b10 l
19
b1111 8
b1111 =
b1111 M
b1111 ^
05
#285000
0N
0>
b1010101 T
b111 \
b1111 W
b111 Z
b100 L
b1111 G
b101010 J
b110 %
b110 m
b1111 X
b1111 H
0#
15
#290000
1]
b110 %
b110 m
b10 "
b10 e
b10 l
b0 8
b0 =
b0 M
b0 ^
09
05
#295000
1>
1N
b100 L
b0 G
b101010 J
b1000110 T
b111 \
b0 W
b111 Z
b0 H
b0 X
15
#300000
05
#305000
15
#310000
0]
b110 %
b110 m
1(
b10 "
b10 e
b10 l
19
b1100 8
b1100 =
b1100 M
b1100 ^
05
#315000
b0 D
b0 L
b0 J
b0 "
b0 e
b0 l
1(
b0 %
b0 m
b0 T
b0 \
b0 Z
b0 d
b0 K
03
b0 .
b0 E
14
b0 '
b0 I
b0 i
b0 H
b0 [
01
b0 -
b0 U
12
b0 &
b0 Y
b0 j
b0 X
15
#320000
1]
0(
b0 8
b0 =
b0 M
b0 ^
09
05
#325000
15
#330000
05
#335000
15
#340000
1,
19
b101 8
b101 =
b101 M
b101 ^
05
#345000
b101 T
b101 W
b101 D
b101 G
b101 X
b101 H
1F
15
#350000
0,
b0 8
b0 =
b0 M
b0 ^
09
05
#355000
b101 %
b101 m
b110010 D
b101 L
b0 G
b101 J
b0 T
b0 W
b101 K
b1 .
b1 E
04
b101 '
b101 I
b101 i
b0 H
0F
b0 X
15
#360000
05
#365000
15
#370000
1,
19
b110 8
b110 =
b110 M
b110 ^
05
#375000
b111000 D
b101 L
b110 G
b101 J
b110 T
b110 W
b110 H
1F
b110 X
15
#380000
0,
b0 8
b0 =
b0 M
b0 ^
09
05
#385000
b0 T
b0 W
b111000 %
b111000 m
b101 L
b0 G
b111000 J
b0 X
13
b10 .
b10 E
b111000 '
b111000 I
b111000 i
b0 H
0F
15
#390000
05
#395000
15
#400000
0]
10
19
b1011 8
b1011 =
b1011 M
b1011 ^
05
#405000
0N
0>
b1011 T
b1011 W
b101 L
b1011 G
b111000 J
b1011 X
b1011 H
1C
15
#410000
1]
00
b0 8
b0 =
b0 M
b0 ^
09
05
#415000
1>
1N
b101 %
b101 m
b110010 D
b101 L
b0 G
b101 J
b0 T
b0 W
03
b1 .
b1 E
b101 '
b101 I
b101 i
b0 H
0C
b0 X
15
#420000
05
#425000
15
#430000
10
0]
0,
19
b1011 8
b1011 =
b1011 M
b1011 ^
05
#435000
0>
0N
b111101 D
b101 L
b1011 G
b101 J
b1011 T
b1011 W
b1011 H
1C
b1011 X
15
#440000
1]
00
b0 8
b0 =
b0 M
b0 ^
09
05
#445000
1N
1>
b0 T
b0 W
b0 %
b0 m
b0 D
b0 L
b0 G
b0 J
b0 X
b0 K
b0 .
b0 E
14
b0 '
b0 I
b0 i
b0 H
0C
15
#450000
05
#455000
15
#460000
0]
1(
19
b1100 8
b1100 =
b1100 M
b1100 ^
05
#465000
b0 X
b0 H
15
#470000
1]
0(
b0 8
b0 =
b0 M
b0 ^
09
05
#475000
15
#480000
05
#485000
15
#490000
1,
19
b110 8
b110 =
b110 M
b110 ^
05
#495000
b110 D
b110 G
b110 T
b110 W
b110 H
1F
b110 X
15
#500000
0,
b0 8
b0 =
b0 M
b0 ^
09
05
#505000
b0 T
b0 W
b110 %
b110 m
b111100 D
b110 L
b0 G
b110 J
b0 X
b110 K
b1 .
b1 E
04
b110 '
b110 I
b110 i
b0 H
0F
15
#510000
05
#515000
15
#520000
1,
19
b100 8
b100 =
b100 M
b100 ^
05
#525000
b100 T
b100 W
b1000000 D
b110 L
b100 G
b110 J
b100 X
b100 H
1F
15
#530000
0,
b0 8
b0 =
b0 M
b0 ^
09
05
#535000
b111100 D
b110 L
b0 G
b110 J
b0 T
b0 W
b0 H
0F
b0 X
15
#540000
05
#545000
15
#550000
0]
1(
19
b1100 8
b1100 =
b1100 M
b1100 ^
05
#555000
b0 %
b0 m
b0 D
b0 L
b0 J
b0 K
b0 .
b0 E
14
b0 '
b0 I
b0 i
b0 H
b0 X
15
#560000
1]
0(
b0 8
b0 =
b0 M
b0 ^
09
05
#565000
15
#570000
05
#575000
15
#580000
1,
19
b1 8
b1 =
b1 M
b1 ^
05
#585000
b1 T
b1 W
b1 D
b1 G
b1 X
b1 H
1F
15
#590000
0,
b0 8
b0 =
b0 M
b0 ^
09
05
