src/Modulos/Calculo_DivEnt/subsistema_division.sv
module subsistema_division (
    input wire clk,             // Señal de reloj
    input wire rst,             // Señal de reinicio (activo en alto)
    input wire [5:0] A,         // Dividendo de 6 bits
    input wire [3:0] B,         // Divisor de 4 bits
    input wire valid,           // Bandera de inicio de operación
    output reg [5:0] cociente,  // Cociente de la división
    output reg [3:0] residuo,   // Residuo de la división
    output reg done             // Bandera de resultado estable
);

    // Definición de los estados
    localparam ESPERA = 1'b0;
    localparam CALCULO = 1'b1;

    reg estado_actual;

    always @(posedge clk or posedge rst) begin
        if (rst) begin
            // Reinicio de todos los registros
            estado_actual <= ESPERA;
            cociente <= 6'b000000;
            residuo <= 4'b0000;
            done <= 1'b0;
        end else begin
            case (estado_actual)
                ESPERA: begin
                    done <= 1'b0; // Se apaga la bandera done
                    
                    // Condición 2: Inicia cuando valid es 1
                    if (valid) begin
                        estado_actual <= CALCULO;
                    end
                end

                CALCULO: begin
                    // Prevención de error matemático (división por cero)
                    if (B != 4'b0000) begin
                        cociente <= A / B;
                        residuo  <= A % B;
                    end else begin
                        // Manejo de error si B es 0
                        cociente <= 6'b111111; 
                        residuo  <= 4'b0000;
                    end
                    
                    // Condición 3: Se levanta la bandera done al tener resultado estable
                    done <= 1'b1;
                    
                    // Regresa al estado de espera para la siguiente operación
                    estado_actual <= ESPERA;
                end
            endcase
        end
    end

endmodule

src/UnidadPrincipal/sim/tb_subsistema_division.sv
`timescale 1ns/1ps

module tb_subsistema_division;

    // Señales del testbench
    reg clk;
    reg rst;
    reg [5:0] A;
    reg [3:0] B;
    reg valid;

    wire [5:0] cociente;
    wire [3:0] residuo;
    wire done;

    integer errores;

    // Instancia del módulo a probar
    subsistema_division dut (
        .clk(clk),
        .rst(rst),
        .A(A),
        .B(B),
        .valid(valid),
        .cociente(cociente),
        .residuo(residuo),
        .done(done)
    );

    // Generador de reloj
    // Periodo = 10 ns
    always #5 clk = ~clk;

    // Tarea para probar una división
    task probar_division;
        input [5:0] entrada_A;
        input [3:0] entrada_B;
        input [5:0] esperado_cociente;
        input [3:0] esperado_residuo;

        begin
            // Poner entradas antes del flanco de subida
            @(negedge clk);
            A = entrada_A;
            B = entrada_B;
            valid = 1'b1;

            // Mantener valid activo solo un ciclo
            @(negedge clk);
            valid = 1'b0;

            // Esperar a que done se active
            wait(done == 1'b1);
            #1;

            // Verificación de resultados
            if (cociente === esperado_cociente && residuo === esperado_residuo) begin
                $display("OK: A=%0d, B=%0d -> cociente=%0d, residuo=%0d",
                         entrada_A, entrada_B, cociente, residuo);
            end else begin
                $display("ERROR: A=%0d, B=%0d", entrada_A, entrada_B);
                $display("       Esperado: cociente=%0d, residuo=%0d",
                         esperado_cociente, esperado_residuo);
                $display("       Obtenido: cociente=%0d, residuo=%0d",
                         cociente, residuo);
                errores = errores + 1;
            end

            // Esperar a que el módulo vuelva a ESPERA y done baje
            @(posedge clk);
        end
    endtask

    initial begin
        // Archivo para GTKWave
        $dumpfile("tb_subsistema_division.vcd");
        $dumpvars(0, tb_subsistema_division);

        // Inicialización
        clk = 1'b0;
        rst = 1'b1;
        A = 6'd0;
        B = 4'd0;
        valid = 1'b0;
        errores = 0;

        // Reset inicial
        #20;
        rst = 1'b0;

        $display("Iniciando pruebas del subsistema_division...");

        // Pruebas normales
        probar_division(6'd20, 4'd4,  6'd5,  4'd0);  // 20 / 4 = 5 residuo 0
        probar_division(6'd25, 4'd4,  6'd6,  4'd1);  // 25 / 4 = 6 residuo 1
        probar_division(6'd63, 4'd15, 6'd4,  4'd3);  // 63 / 15 = 4 residuo 3
        probar_division(6'd7,  4'd2,  6'd3,  4'd1);  // 7 / 2 = 3 residuo 1
        probar_division(6'd0,  4'd5,  6'd0,  4'd0);  // 0 / 5 = 0 residuo 0

        // Prueba de división por cero
        probar_division(6'd30, 4'd0,  6'b111111, 4'd0);

        // Resultado final
        if (errores == 0) begin
            $display("Todas las pruebas pasaron correctamente.");
        end else begin
            $display("Cantidad de errores: %0d", errores);
        end

        #20;
        $finish;
    end

endmodule

src/UnidadPrincipal/build/tb_subsistema_division.vcd
$date
	Tue Jun 09 22:24:57 2026
$end
$version
	Icarus Verilog
$end
$timescale
	1ps
$end
$scope module tb_subsistema_division $end
$var wire 4 ! residuo [3:0] $end
$var wire 1 " done $end
$var wire 6 # cociente [5:0] $end
$var reg 6 $ A [5:0] $end
$var reg 4 % B [3:0] $end
$var reg 1 & clk $end
$var reg 1 ' rst $end
$var reg 1 ( valid $end
$var integer 32 ) errores [31:0] $end
$scope module dut $end
$var wire 6 * A [5:0] $end
$var wire 4 + B [3:0] $end
$var wire 1 & clk $end
$var wire 1 ' rst $end
$var wire 1 ( valid $end
$var parameter 1 , CALCULO $end
$var parameter 1 - ESPERA $end
$var reg 6 . cociente [5:0] $end
$var reg 1 " done $end
$var reg 1 / estado_actual $end
$var reg 4 0 residuo [3:0] $end
$upscope $end
$scope task probar_division $end
$var reg 6 1 entrada_A [5:0] $end
$var reg 4 2 entrada_B [3:0] $end
$var reg 6 3 esperado_cociente [5:0] $end
$var reg 4 4 esperado_residuo [3:0] $end
$upscope $end
$upscope $end
$enddefinitions $end
$comment Show the parameter values. $end
$dumpall
0-
1,
$end
#0
$dumpvars
bx 4
bx 3
bx 2
bx 1
b0 0
0/
b0 .
b0 +
b0 *
b0 )
0(
1'
0&
b0 %
b0 $
b0 #
0"
b0 !
$end
#5000
1&
#10000
0&
#15000
1&
#20000
1(
b100 %
b100 +
b10100 $
b10100 *
0&
b0 4
b101 3
b100 2
b10100 1
0'
#25000
1/
1&
#30000
0(
0&
#35000
0/
1"
b101 #
b101 .
1&
#40000
0&
#45000
0"
b1 4
b110 3
b11001 1
1&
#50000
1(
b11001 $
b11001 *
0&
#55000
1/
1&
#60000
0(
0&
#65000
0/
1"
b1 !
b1 0
b110 #
b110 .
1&
#70000
0&
#75000
0"
b11 4
b100 3
b1111 2
b111111 1
1&
#80000
1(
b1111 %
b1111 +
b111111 $
b111111 *
0&
#85000
1/
1&
#90000
0(
0&
#95000
0/
1"
b11 !
b11 0
b100 #
b100 .
1&
#100000
0&
#105000
0"
b1 4
b11 3
b10 2
b111 1
1&
#110000
1(
b10 %
b10 +
b111 $
b111 *
0&
#115000
1/
1&
#120000
0(
0&
#125000
0/
1"
b1 !
b1 0
b11 #
b11 .
1&
#130000
0&
#135000
0"
b0 4
b0 3
b101 2
b0 1
1&
#140000
1(
b101 %
b101 +
b0 $
b0 *
0&
#145000
1/
1&
#150000
0(
0&
#155000
0/
1"
b0 !
b0 0
b0 #
b0 .
1&
#160000
0&
#165000
0"
b111111 3
b0 2
b11110 1
1&
#170000
1(
b0 %
b0 +
b11110 $
b11110 *
0&
#175000
1/
1&
#180000
0(
0&
#185000
0/
1"
b111111 #
b111111 .
1&
#190000
0&
#195000
0"
1&
